rrm/__init__.py
rrm/__main__.py
rrm-0.1.1.dist-info/entry_points.txt
rrm-0.1.1.dist-info/LICENSE
rrm-0.1.1.dist-info/WHEEL
rrm-0.1.1.dist-info/METADATA
rrm-0.1.1.dist-info/RECORD
