Metadata-Version: 2.1
Name: rrm
Version: 0.1.1
Summary: Really, relentlessly and repeatedly remove files and all of their copies.
Home-page: https://gitlab.com/szs/rrm/
License: MIT
Keywords: terminal,console,command line,system tool,cli
Author: Steffen Brinkmann
Author-email: s-b@mailbox.org
Requires-Python: >=3.9,<4.0
Classifier: Development Status :: 4 - Beta
Classifier: Environment :: Console
Classifier: Intended Audience :: System Administrators
Classifier: License :: OSI Approved :: MIT License
Classifier: Programming Language :: Python :: 3
Classifier: Programming Language :: Python :: 3.6
Classifier: Programming Language :: Python :: 3.7
Classifier: Programming Language :: Python :: 3.8
Classifier: Programming Language :: Python :: 3.9
Classifier: Topic :: System
Classifier: Topic :: Utilities
Project-URL: Repository, https://gitlab.com/szs/rrm/
